[
    {
        "title": "Бесплатная консультация",
        "description": "Новые клиенты могут получить бесплатную консультацию",
        "image": "/features/noun_branding_1885335.svg"
    },
    {
        "title": "Cпециалисты",
        "description": "Команда высококвалифицированных специалистов",
        "image": "/features/noun_The Process_1885341.svg"
    },
    {
        "title": "Стоимость",
        "description": "Предлагаем приемлемую стоимость переплетных работ.",
        "image": "/features/noun_3d modeling_1885342.svg"
    }
]
